stealthenium/__init__.py
stealthenium/cdp.py
stealthenium/chrome_app.py
stealthenium/chrome_runtime.py
stealthenium/hairline_fix.py
stealthenium/iframe_content_window.py
stealthenium/media_codecs.py
stealthenium/navigator_languages.py
stealthenium/navigator_permissions.py
stealthenium/navigator_plugins.py
stealthenium/navigator_vendor.py
stealthenium/navigator_webdriver.py
stealthenium/user_agent_override.py
stealthenium/utils.py
stealthenium/webgl_vendor.py
stealthenium/window_outerdimensions.py
stealthenium/wrapper.py
stealthenium/js/chrome.app.js
stealthenium/js/chrome.csi.js
stealthenium/js/chrome.loadTimes.js
stealthenium/js/chrome.runtime.js
stealthenium/js/hairline.fix.js
stealthenium/js/iframe.contentWindow.js
stealthenium/js/media.codecs.js
stealthenium/js/navigator.languages.js
stealthenium/js/navigator.permissions.js
stealthenium/js/navigator.plugins.js
stealthenium/js/navigator.vendor.js
stealthenium/js/navigator.webdriver.js
stealthenium/js/utils.js
stealthenium/js/webgl.vendor.js
stealthenium/js/window.outerdimensions.js
stealthenium-1.1.0.dist-info/LICENSE.txt
stealthenium-1.1.0.dist-info/METADATA
stealthenium-1.1.0.dist-info/WHEEL
stealthenium-1.1.0.dist-info/top_level.txt
stealthenium-1.1.0.dist-info/RECORD
