Metadata-Version: 2.1
Name: stealthenium
Version: 1.1.0
Summary: A wrapper to make python selenium stealthy.
Home-page: https://github.com/markmelnic/stealthenium
Author: Mark Melnic
Author-email: markmelnic@gmail.com
Classifier: License :: OSI Approved :: MIT License
Classifier: Operating System :: OS Independent
Classifier: Environment :: Console
Classifier: Environment :: MacOS X
Classifier: Environment :: Win32 (MS Windows)
Classifier: Environment :: Web Environment
Classifier: Framework :: Pytest
Classifier: Intended Audience :: Developers
Classifier: Intended Audience :: Information Technology
Classifier: License :: OSI Approved :: MIT License
Classifier: Operating System :: MacOS :: MacOS X
Classifier: Operating System :: Microsoft :: Windows
Classifier: Operating System :: POSIX :: Linux
Classifier: Programming Language :: Python
Classifier: Programming Language :: Python :: 3.7
Classifier: Programming Language :: Python :: 3.8
Classifier: Programming Language :: Python :: 3.9
Classifier: Programming Language :: Python :: 3.10
Classifier: Programming Language :: Python :: 3.11
Classifier: Topic :: Internet
Classifier: Topic :: Scientific/Engineering
Classifier: Topic :: Software Development
Classifier: Topic :: Software Development :: Quality Assurance
Classifier: Topic :: Software Development :: Libraries
Classifier: Topic :: Software Development :: Testing
Classifier: Topic :: Software Development :: Testing :: Acceptance
Classifier: Topic :: Software Development :: Testing :: Traffic Generation
Classifier: Topic :: Utilities
Requires-Python: >=3, !=3.0.*, !=3.1.*, !=3.2.*, !=3.3.*, !=3.4.*
License-File: LICENSE.txt
Requires-Dist: selenium
Provides-Extra: test
Requires-Dist: pytest; extra == "test"
